ark_toml.py
ark_toml-0.1.0.dist-info/METADATA
ark_toml-0.1.0.dist-info/WHEEL
ark_toml-0.1.0.dist-info/top_level.txt
ark_toml-0.1.0.dist-info/RECORD
