Metadata-Version: 2.1
Name: ark-toml
Version: 0.1.0
Summary: Adds TOML support to Ark.
Home-page: https://github.com/dmulholl/ark-toml
Author: Darren Mulholland
License: Public Domain
Classifier: Programming Language :: Python :: 3
Classifier: Operating System :: OS Independent
Classifier: License :: Public Domain
Requires-Dist: toml (~=0.10)
